detective/__init__.py
detective/auth.py
detective/config.py
detective/core.py
detective/functions.py
detective/time.py
HASS_data_detective-3.0.dist-info/LICENSE
HASS_data_detective-3.0.dist-info/METADATA
HASS_data_detective-3.0.dist-info/WHEEL
HASS_data_detective-3.0.dist-info/top_level.txt
HASS_data_detective-3.0.dist-info/RECORD
