Metadata-Version: 2.1
Name: HASS-data-detective
Version: 3.0
Summary: Tools for studying Home Assistant data.
Home-page: https://github.com/robmarkcole/HASS-data-detective
Author: Robin Cole
Author-email: robmarkcole@gmail.com
License: MIT
Keywords: home,automation
Classifier: Development Status :: 4 - Beta
Classifier: Intended Audience :: Developers
Classifier: License :: OSI Approved :: MIT License
Classifier: Natural Language :: English
Classifier: Programming Language :: Python
Classifier: Programming Language :: Python :: 3
License-File: LICENSE
Requires-Dist: pandas (>=1.1.4)
Requires-Dist: ruamel.yaml (>=0.15.78)
Requires-Dist: SQLAlchemy (>=2.0.7)
Requires-Dist: pytz
